README.rst
setup.cfg
setup.py
ksql/__init__.py
ksql/api.py
ksql/builder.py
ksql/client.py
ksql/errors.py
ksql/upload.py
ksql.egg-info/PKG-INFO
ksql.egg-info/SOURCES.txt
ksql.egg-info/dependency_links.txt
ksql.egg-info/requires.txt
ksql.egg-info/top_level.txt