Metadata-Version: 1.1
Name: ksql
Version: 0.5.1
Summary: A Python wrapper for the KSql REST API
Home-page: https://github.com/bryanyang0528/ksql-python
Author: Bryan Yang @ Vpon
Author-email: kenshin200528@gmail.com
License: MIT License
Platform: any
Classifier: Development Status :: 5 - Production/Stable
Classifier: Intended Audience :: Developers
Classifier: Natural Language :: English
Classifier: License :: OSI Approved :: MIT License
Classifier: Programming Language :: Python
Classifier: Programming Language :: Python :: 2.7
Classifier: Programming Language :: Python :: 3.3
Classifier: Programming Language :: Python :: 3.4
Classifier: Programming Language :: Python :: 3.5
Classifier: Programming Language :: Python :: 3.6
Classifier: Topic :: Software Development :: Libraries :: Python Modules
